<?xml version="1.0" encoding="utf-8"?>
<QuickPlayBundle name="Bundle 3" id="3" version="0" date="1675173981">
    <items>
        <QuickPlayBundleItem sid="2919986332" x="0" y="0" w="2" h="2" />
        <QuickPlayBundleItem sid="2921614965" x="2" y="0" w="1" h="1" />
        <QuickPlayBundleItem sid="2914267894" x="2" y="1" w="1" h="1" />

        <QuickPlayBundleItem sid="2882151753" x="0" y="2" w="1" h="1" />
        <QuickPlayBundleItem sid="2926343830" x="1" y="2" w="1" h="1" />
        <QuickPlayBundleItem sid="2914459138" x="2" y="2" w="1" h="1" />
    </items>
</QuickPlayBundle>